{
    "total": 55588,
    "total_pages": 5559,
    "results": [
        {
            "id": "VmX3vmBecFE",
            "created_at": "2018-02-24T14:42:46-05:00",
            "updated_at": "2019-03-27T18:08:40-04:00",
            "width": 4912,
            "height": 6144,
            "color": "#F1DAD0",
            "description": "Caught this photo walking around after work. Streets were packed with cars and the sun was setting and it made me so glad that I was driving and could just be taking pictures.",
            "alt_description": "vehicles near buildings at night time",
            "urls": {
                "raw": "https://images.unsplash.com/photo-1519501025264-65ba15a82390?ixlib=rb-1.2.1&ixid=eyJhcHBfaWQiOjY2Njc0fQ",
                "full": "https://images.unsplash.com/photo-1519501025264-65ba15a82390?ixlib=rb-1.2.1&q=85&fm=jpg&crop=entropy&cs=srgb&ixid=eyJhcHBfaWQiOjY2Njc0fQ",
                "regular": "https://images.unsplash.com/photo-1519501025264-65ba15a82390?ixlib=rb-1.2.1&q=80&fm=jpg&crop=entropy&cs=tinysrgb&w=1080&fit=max&ixid=eyJhcHBfaWQiOjY2Njc0fQ",
                "small": "https://images.unsplash.com/photo-1519501025264-65ba15a82390?ixlib=rb-1.2.1&q=80&fm=jpg&crop=entropy&cs=tinysrgb&w=400&fit=max&ixid=eyJhcHBfaWQiOjY2Njc0fQ",
                "thumb": "https://images.unsplash.com/photo-1519501025264-65ba15a82390?ixlib=rb-1.2.1&q=80&fm=jpg&crop=entropy&cs=tinysrgb&w=200&fit=max&ixid=eyJhcHBfaWQiOjY2Njc0fQ"
            },
            "links": {
                "self": "https://api.unsplash.com/photos/VmX3vmBecFE",
                "html": "https://unsplash.com/photos/VmX3vmBecFE",
                "download": "https://unsplash.com/photos/VmX3vmBecFE/download",
                "download_location": "https://api.unsplash.com/photos/VmX3vmBecFE/download"
            },
            "categories": [],
            "sponsored": false,
            "sponsored_by": null,
            "sponsored_impressions_id": null,
            "likes": 555,
            "liked_by_user": false,
            "current_user_collections": [],
            "user": {
                "id": "JuqHbHtpPDE",
                "updated_at": "2019-04-13T20:50:23-04:00",
                "username": "maxwbender",
                "name": "Max Bender",
                "first_name": "Max",
                "last_name": "Bender",
                "twitter_username": null,
                "portfolio_url": "https://www.instagram.com/maxwbender/",
                "bio": "Say hi or start a project | DM or email | Stay lit fam",
                "location": "Chicago IL",
                "links": {
                    "self": "https://api.unsplash.com/users/maxwbender",
                    "html": "https://unsplash.com/@maxwbender",
                    "photos": "https://api.unsplash.com/users/maxwbender/photos",
                    "likes": "https://api.unsplash.com/users/maxwbender/likes",
                    "portfolio": "https://api.unsplash.com/users/maxwbender/portfolio",
                    "following": "https://api.unsplash.com/users/maxwbender/following",
                    "followers": "https://api.unsplash.com/users/maxwbender/followers"
                },
                "profile_image": {
                    "small": "https://images.unsplash.com/profile-1541082497584-73f391a8da0f?ixlib=rb-1.2.1&q=80&fm=jpg&crop=faces&cs=tinysrgb&fit=crop&h=32&w=32",
                    "medium": "https://images.unsplash.com/profile-1541082497584-73f391a8da0f?ixlib=rb-1.2.1&q=80&fm=jpg&crop=faces&cs=tinysrgb&fit=crop&h=64&w=64",
                    "large": "https://images.unsplash.com/profile-1541082497584-73f391a8da0f?ixlib=rb-1.2.1&q=80&fm=jpg&crop=faces&cs=tinysrgb&fit=crop&h=128&w=128"
                },
                "instagram_username": "maxwbender",
                "total_collections": 26,
                "total_likes": 1639,
                "total_photos": 150,
                "accepted_tos": true
            },
            "tags": [
                {
                    "title": "street"
                },
                {
                    "title": "cars"
                },
                {
                    "title": "buildings"
                },
                {
                    "title": "reflection"
                },
                {
                    "title": "blue"
                },
                {
                    "title": "red"
                },
                {
                    "title": "purple"
                },
                {
                    "title": "traffic"
                },
                {
                    "title": "headlights"
                },
                {
                    "title": "evening"
                }
            ]
        },
        {
            "id": "s4I1xpX_ny8",
            "created_at": "2018-03-02T09:03:59-05:00",
            "updated_at": "2019-03-27T18:09:06-04:00",
            "width": 4473,
            "height": 3576,
            "color": "#FED6AA",
            "description": "Got this photo from a rooftop at sunset. I didn’t even realize how cold it was out till I went back inside, the view had me completely entranced.",
            "alt_description": "high-rise building during golden hour",
            "urls": {
                "raw": "https://images.unsplash.com/photo-1519999482648-25049ddd37b1?ixlib=rb-1.2.1&ixid=eyJhcHBfaWQiOjY2Njc0fQ",
                "full": "https://images.unsplash.com/photo-1519999482648-25049ddd37b1?ixlib=rb-1.2.1&q=85&fm=jpg&crop=entropy&cs=srgb&ixid=eyJhcHBfaWQiOjY2Njc0fQ",
                "regular": "https://images.unsplash.com/photo-1519999482648-25049ddd37b1?ixlib=rb-1.2.1&q=80&fm=jpg&crop=entropy&cs=tinysrgb&w=1080&fit=max&ixid=eyJhcHBfaWQiOjY2Njc0fQ",
                "small": "https://images.unsplash.com/photo-1519999482648-25049ddd37b1?ixlib=rb-1.2.1&q=80&fm=jpg&crop=entropy&cs=tinysrgb&w=400&fit=max&ixid=eyJhcHBfaWQiOjY2Njc0fQ",
                "thumb": "https://images.unsplash.com/photo-1519999482648-25049ddd37b1?ixlib=rb-1.2.1&q=80&fm=jpg&crop=entropy&cs=tinysrgb&w=200&fit=max&ixid=eyJhcHBfaWQiOjY2Njc0fQ"
            },
            "links": {
                "self": "https://api.unsplash.com/photos/s4I1xpX_ny8",
                "html": "https://unsplash.com/photos/s4I1xpX_ny8",
                "download": "https://unsplash.com/photos/s4I1xpX_ny8/download",
                "download_location": "https://api.unsplash.com/photos/s4I1xpX_ny8/download"
            },
            "categories": [],
            "sponsored": false,
            "sponsored_by": null,
            "sponsored_impressions_id": null,
            "likes": 593,
            "liked_by_user": false,
            "current_user_collections": [],
            "user": {
                "id": "JuqHbHtpPDE",
                "updated_at": "2019-04-13T20:50:23-04:00",
                "username": "maxwbender",
                "name": "Max Bender",
                "first_name": "Max",
                "last_name": "Bender",
                "twitter_username": null,
                "portfolio_url": "https://www.instagram.com/maxwbender/",
                "bio": "Say hi or start a project | DM or email | Stay lit fam",
                "location": "Chicago IL",
                "links": {
                    "self": "https://api.unsplash.com/users/maxwbender",
                    "html": "https://unsplash.com/@maxwbender",
                    "photos": "https://api.unsplash.com/users/maxwbender/photos",
                    "likes": "https://api.unsplash.com/users/maxwbender/likes",
                    "portfolio": "https://api.unsplash.com/users/maxwbender/portfolio",
                    "following": "https://api.unsplash.com/users/maxwbender/following",
                    "followers": "https://api.unsplash.com/users/maxwbender/followers"
                },
                "profile_image": {
                    "small": "https://images.unsplash.com/profile-1541082497584-73f391a8da0f?ixlib=rb-1.2.1&q=80&fm=jpg&crop=faces&cs=tinysrgb&fit=crop&h=32&w=32",
                    "medium": "https://images.unsplash.com/profile-1541082497584-73f391a8da0f?ixlib=rb-1.2.1&q=80&fm=jpg&crop=faces&cs=tinysrgb&fit=crop&h=64&w=64",
                    "large": "https://images.unsplash.com/profile-1541082497584-73f391a8da0f?ixlib=rb-1.2.1&q=80&fm=jpg&crop=faces&cs=tinysrgb&fit=crop&h=128&w=128"
                },
                "instagram_username": "maxwbender",
                "total_collections": 26,
                "total_likes": 1639,
                "total_photos": 150,
                "accepted_tos": true
            },
            "tags": [
                {
                    "title": "bridge"
                },
                {
                    "title": "river"
                },
                {
                    "title": "skyscraper"
                },
                {
                    "title": "night"
                },
                {
                    "title": "street"
                },
                {
                    "title": "building"
                },
                {
                    "title": "urban"
                },
                {
                    "title": "dusk"
                },
                {
                    "title": "sunset"
                },
                {
                    "title": "city at night"
                },
                {
                    "title": "night lights"
                },
                {
                    "title": "modern architecture"
                },
                {
                    "title": "building complex"
                },
                {
                    "title": "chicago"
                }
            ]
        },
        {
            "id": "wpU4veNGnHg",
            "created_at": "2016-12-02T16:36:41-05:00",
            "updated_at": "2019-03-27T17:47:28-04:00",
            "width": 5472,
            "height": 3648,
            "color": "#0D0C0D",
            "description": "7am shot",
            "alt_description": "high rise buildings city scape photography",
            "urls": {
                "raw": "https://images.unsplash.com/photo-1480714378408-67cf0d13bc1b?ixlib=rb-1.2.1&ixid=eyJhcHBfaWQiOjY2Njc0fQ",
                "full": "https://images.unsplash.com/photo-1480714378408-67cf0d13bc1b?ixlib=rb-1.2.1&q=85&fm=jpg&crop=entropy&cs=srgb&ixid=eyJhcHBfaWQiOjY2Njc0fQ",
                "regular": "https://images.unsplash.com/photo-1480714378408-67cf0d13bc1b?ixlib=rb-1.2.1&q=80&fm=jpg&crop=entropy&cs=tinysrgb&w=1080&fit=max&ixid=eyJhcHBfaWQiOjY2Njc0fQ",
                "small": "https://images.unsplash.com/photo-1480714378408-67cf0d13bc1b?ixlib=rb-1.2.1&q=80&fm=jpg&crop=entropy&cs=tinysrgb&w=400&fit=max&ixid=eyJhcHBfaWQiOjY2Njc0fQ",
                "thumb": "https://images.unsplash.com/photo-1480714378408-67cf0d13bc1b?ixlib=rb-1.2.1&q=80&fm=jpg&crop=entropy&cs=tinysrgb&w=200&fit=max&ixid=eyJhcHBfaWQiOjY2Njc0fQ"
            },
            "links": {
                "self": "https://api.unsplash.com/photos/wpU4veNGnHg",
                "html": "https://unsplash.com/photos/wpU4veNGnHg",
                "download": "https://unsplash.com/photos/wpU4veNGnHg/download",
                "download_location": "https://api.unsplash.com/photos/wpU4veNGnHg/download"
            },
            "categories": [],
            "sponsored": false,
            "sponsored_by": null,
            "sponsored_impressions_id": null,
            "likes": 548,
            "liked_by_user": false,
            "current_user_collections": [],
            "user": {
                "id": "DE2lKLbSMug",
                "updated_at": "2019-02-21T05:05:25-05:00",
                "username": "benobro",
                "name": "ben o'bro",
                "first_name": "ben",
                "last_name": "o'bro",
                "twitter_username": null,
                "portfolio_url": "http://www.benobro.com",
                "bio": null,
                "location": "GVA",
                "links": {
                    "self": "https://api.unsplash.com/users/benobro",
                    "html": "https://unsplash.com/@benobro",
                    "photos": "https://api.unsplash.com/users/benobro/photos",
                    "likes": "https://api.unsplash.com/users/benobro/likes",
                    "portfolio": "https://api.unsplash.com/users/benobro/portfolio",
                    "following": "https://api.unsplash.com/users/benobro/following",
                    "followers": "https://api.unsplash.com/users/benobro/followers"
                },
                "profile_image": {
                    "small": "https://images.unsplash.com/profile-1515016860295-94be36a36d1d?ixlib=rb-1.2.1&q=80&fm=jpg&crop=faces&cs=tinysrgb&fit=crop&h=32&w=32",
                    "medium": "https://images.unsplash.com/profile-1515016860295-94be36a36d1d?ixlib=rb-1.2.1&q=80&fm=jpg&crop=faces&cs=tinysrgb&fit=crop&h=64&w=64",
                    "large": "https://images.unsplash.com/profile-1515016860295-94be36a36d1d?ixlib=rb-1.2.1&q=80&fm=jpg&crop=faces&cs=tinysrgb&fit=crop&h=128&w=128"
                },
                "instagram_username": "benobro",
                "total_collections": 0,
                "total_likes": 69,
                "total_photos": 12,
                "accepted_tos": false
            },
            "tags": [
                {
                    "title": "building"
                },
                {
                    "title": "skyscraper"
                },
                {
                    "title": "architecture"
                },
                {
                    "title": "cityscape"
                },
                {
                    "title": "metropolitan"
                },
                {
                    "title": "downtown"
                },
                {
                    "title": "metropoli"
                },
                {
                    "title": "sunrise"
                },
                {
                    "title": "sunset"
                },
                {
                    "title": "evening"
                },
                {
                    "title": "usa"
                },
                {
                    "title": "new york"
                },
                {
                    "title": "skyline"
                },
                {
                    "title": "united state"
                }
            ]
        },
        {
            "id": "Ys-DBJeX0nE",
            "created_at": "2017-07-31T23:21:28-04:00",
            "updated_at": "2019-04-14T17:40:35-04:00",
            "width": 4896,
            "height": 3264,
            "color": "#F0EFEE",
            "description": "We were having a BBQ on a rooftop while it was pouring rain and while we got extremely wet, I was lucky enough to get some beautiful photos of the city’s glow and everyone still had fun.",
            "alt_description": "skyline photography of cityscape",
            "urls": {
                "raw": "https://images.unsplash.com/Ys-DBJeX0nE.JPG?ixlib=rb-1.2.1&ixid=eyJhcHBfaWQiOjY2Njc0fQ",
                "full": "https://images.unsplash.com/Ys-DBJeX0nE.JPG?ixlib=rb-1.2.1&q=85&fm=jpg&crop=entropy&cs=srgb&ixid=eyJhcHBfaWQiOjY2Njc0fQ",
                "regular": "https://images.unsplash.com/Ys-DBJeX0nE.JPG?ixlib=rb-1.2.1&q=80&fm=jpg&crop=entropy&cs=tinysrgb&w=1080&fit=max&ixid=eyJhcHBfaWQiOjY2Njc0fQ",
                "small": "https://images.unsplash.com/Ys-DBJeX0nE.JPG?ixlib=rb-1.2.1&q=80&fm=jpg&crop=entropy&cs=tinysrgb&w=400&fit=max&ixid=eyJhcHBfaWQiOjY2Njc0fQ",
                "thumb": "https://images.unsplash.com/Ys-DBJeX0nE.JPG?ixlib=rb-1.2.1&q=80&fm=jpg&crop=entropy&cs=tinysrgb&w=200&fit=max&ixid=eyJhcHBfaWQiOjY2Njc0fQ"
            },
            "links": {
                "self": "https://api.unsplash.com/photos/Ys-DBJeX0nE",
                "html": "https://unsplash.com/photos/Ys-DBJeX0nE",
                "download": "https://unsplash.com/photos/Ys-DBJeX0nE/download",
                "download_location": "https://api.unsplash.com/photos/Ys-DBJeX0nE/download"
            },
            "categories": [],
            "sponsored": false,
            "sponsored_by": null,
            "sponsored_impressions_id": null,
            "likes": 526,
            "liked_by_user": false,
            "current_user_collections": [],
            "user": {
                "id": "oOg8lRiuXvU",
                "updated_at": "2019-04-14T07:25:55-04:00",
                "username": "agkdesign",
                "name": "Alex Knight",
                "first_name": "Alex",
                "last_name": "Knight",
                "twitter_username": "agkdesign",
                "portfolio_url": "http://www.agkdesigns.net",
                "bio": "UX/UI designer living in Tokyo",
                "location": "Tokyo",
                "links": {
                    "self": "https://api.unsplash.com/users/agkdesign",
                    "html": "https://unsplash.com/@agkdesign",
                    "photos": "https://api.unsplash.com/users/agkdesign/photos",
                    "likes": "https://api.unsplash.com/users/agkdesign/likes",
                    "portfolio": "https://api.unsplash.com/users/agkdesign/portfolio",
                    "following": "https://api.unsplash.com/users/agkdesign/following",
                    "followers": "https://api.unsplash.com/users/agkdesign/followers"
                },
                "profile_image": {
                    "small": "https://images.unsplash.com/profile-1485919296305-2617a7f696c4?ixlib=rb-1.2.1&q=80&fm=jpg&crop=faces&cs=tinysrgb&fit=crop&h=32&w=32",
                    "medium": "https://images.unsplash.com/profile-1485919296305-2617a7f696c4?ixlib=rb-1.2.1&q=80&fm=jpg&crop=faces&cs=tinysrgb&fit=crop&h=64&w=64",
                    "large": "https://images.unsplash.com/profile-1485919296305-2617a7f696c4?ixlib=rb-1.2.1&q=80&fm=jpg&crop=faces&cs=tinysrgb&fit=crop&h=128&w=128"
                },
                "instagram_username": "Agk42",
                "total_collections": 1,
                "total_likes": 977,
                "total_photos": 117,
                "accepted_tos": true
            },
            "tags": [
                {
                    "title": "building"
                },
                {
                    "title": "japan"
                },
                {
                    "title": "bridge"
                },
                {
                    "title": "urban"
                },
                {
                    "title": "night"
                },
                {
                    "title": "waterfront"
                },
                {
                    "title": "factory"
                },
                {
                    "title": "refinery"
                },
                {
                    "title": "skyscraper"
                },
                {
                    "title": "neon"
                },
                {
                    "title": "cyberpunk"
                },
                {
                    "title": "bay"
                },
                {
                    "title": "glow"
                },
                {
                    "title": "water"
                },
                {
                    "title": "skyline"
                },
                {
                    "title": "boat"
                },
                {
                    "title": "cityscape"
                },
                {
                    "title": "town"
                },
                {
                    "title": "minato"
                },
                {
                    "title": "outdoors"
                }
            ]
        },
        {
            "id": "g5Uh7nP60FA",
            "created_at": "2018-04-14T14:48:56-04:00",
            "updated_at": "2019-03-27T18:11:53-04:00",
            "width": 6000,
            "height": 4000,
            "color": "#F6ECD8",
            "description": "Cityscape of Bangkok Downtown",
            "alt_description": "aerial photography of high-rise buildings under cloudy sky",
            "urls": {
                "raw": "https://images.unsplash.com/photo-1523731407965-2430cd12f5e4?ixlib=rb-1.2.1&ixid=eyJhcHBfaWQiOjY2Njc0fQ",
                "full": "https://images.unsplash.com/photo-1523731407965-2430cd12f5e4?ixlib=rb-1.2.1&q=85&fm=jpg&crop=entropy&cs=srgb&ixid=eyJhcHBfaWQiOjY2Njc0fQ",
                "regular": "https://images.unsplash.com/photo-1523731407965-2430cd12f5e4?ixlib=rb-1.2.1&q=80&fm=jpg&crop=entropy&cs=tinysrgb&w=1080&fit=max&ixid=eyJhcHBfaWQiOjY2Njc0fQ",
                "small": "https://images.unsplash.com/photo-1523731407965-2430cd12f5e4?ixlib=rb-1.2.1&q=80&fm=jpg&crop=entropy&cs=tinysrgb&w=400&fit=max&ixid=eyJhcHBfaWQiOjY2Njc0fQ",
                "thumb": "https://images.unsplash.com/photo-1523731407965-2430cd12f5e4?ixlib=rb-1.2.1&q=80&fm=jpg&crop=entropy&cs=tinysrgb&w=200&fit=max&ixid=eyJhcHBfaWQiOjY2Njc0fQ"
            },
            "links": {
                "self": "https://api.unsplash.com/photos/g5Uh7nP60FA",
                "html": "https://unsplash.com/photos/g5Uh7nP60FA",
                "download": "https://unsplash.com/photos/g5Uh7nP60FA/download",
                "download_location": "https://api.unsplash.com/photos/g5Uh7nP60FA/download"
            },
            "categories": [],
            "sponsored": false,
            "sponsored_by": null,
            "sponsored_impressions_id": null,
            "likes": 268,
            "liked_by_user": false,
            "current_user_collections": [],
            "user": {
                "id": "qobw4Dja2Z8",
                "updated_at": "2019-03-28T17:29:01-04:00",
                "username": "andreasbruecker",
                "name": "Andreas Brücker",
                "first_name": "Andreas",
                "last_name": "Brücker",
                "twitter_username": null,
                "portfolio_url": "http://tjp-magazine.com",
                "bio": "Passionate about travelling and urban exploration.\r\n\r\nCreative Director at TJPA",
                "location": "Lisbon",
                "links": {
                    "self": "https://api.unsplash.com/users/andreasbruecker",
                    "html": "https://unsplash.com/@andreasbruecker",
                    "photos": "https://api.unsplash.com/users/andreasbruecker/photos",
                    "likes": "https://api.unsplash.com/users/andreasbruecker/likes",
                    "portfolio": "https://api.unsplash.com/users/andreasbruecker/portfolio",
                    "following": "https://api.unsplash.com/users/andreasbruecker/following",
                    "followers": "https://api.unsplash.com/users/andreasbruecker/followers"
                },
                "profile_image": {
                    "small": "https://images.unsplash.com/profile-1524653061225-27ea03994db2?ixlib=rb-1.2.1&q=80&fm=jpg&crop=faces&cs=tinysrgb&fit=crop&h=32&w=32",
                    "medium": "https://images.unsplash.com/profile-1524653061225-27ea03994db2?ixlib=rb-1.2.1&q=80&fm=jpg&crop=faces&cs=tinysrgb&fit=crop&h=64&w=64",
                    "large": "https://images.unsplash.com/profile-1524653061225-27ea03994db2?ixlib=rb-1.2.1&q=80&fm=jpg&crop=faces&cs=tinysrgb&fit=crop&h=128&w=128"
                },
                "instagram_username": "tjp_mag",
                "total_collections": 1,
                "total_likes": 0,
                "total_photos": 8,
                "accepted_tos": false
            },
            "tags": [
                {
                    "title": "skyscarper"
                },
                {
                    "title": "cityscape"
                },
                {
                    "title": "skyscraper"
                },
                {
                    "title": "from above"
                },
                {
                    "title": "night"
                },
                {
                    "title": "thailand"
                },
                {
                    "title": "bangkok"
                },
                {
                    "title": "drone view"
                },
                {
                    "title": "drone"
                },
                {
                    "title": "skyline"
                },
                {
                    "title": "city by night"
                },
                {
                    "title": "city at night"
                },
                {
                    "title": "city lights"
                },
                {
                    "title": "building"
                },
                {
                    "title": "architectural"
                },
                {
                    "title": "culture"
                },
                {
                    "title": "traveling"
                },
                {
                    "title": "sunset"
                },
                {
                    "title": "city view"
                },
                {
                    "title": "jungle"
                }
            ]
        },
        {
            "id": "Khqmo4T-rs0",
            "created_at": "2018-02-18T22:24:13-05:00",
            "updated_at": "2019-03-27T18:08:15-04:00",
            "width": 2749,
            "height": 4115,
            "color": "#E08635",
            "description": null,
            "alt_description": "city buildings during night time",
            "urls": {
                "raw": "https://images.unsplash.com/photo-1519010470956-6d877008eaa4?ixlib=rb-1.2.1&ixid=eyJhcHBfaWQiOjY2Njc0fQ",
                "full": "https://images.unsplash.com/photo-1519010470956-6d877008eaa4?ixlib=rb-1.2.1&q=85&fm=jpg&crop=entropy&cs=srgb&ixid=eyJhcHBfaWQiOjY2Njc0fQ",
                "regular": "https://images.unsplash.com/photo-1519010470956-6d877008eaa4?ixlib=rb-1.2.1&q=80&fm=jpg&crop=entropy&cs=tinysrgb&w=1080&fit=max&ixid=eyJhcHBfaWQiOjY2Njc0fQ",
                "small": "https://images.unsplash.com/photo-1519010470956-6d877008eaa4?ixlib=rb-1.2.1&q=80&fm=jpg&crop=entropy&cs=tinysrgb&w=400&fit=max&ixid=eyJhcHBfaWQiOjY2Njc0fQ",
                "thumb": "https://images.unsplash.com/photo-1519010470956-6d877008eaa4?ixlib=rb-1.2.1&q=80&fm=jpg&crop=entropy&cs=tinysrgb&w=200&fit=max&ixid=eyJhcHBfaWQiOjY2Njc0fQ"
            },
            "links": {
                "self": "https://api.unsplash.com/photos/Khqmo4T-rs0",
                "html": "https://unsplash.com/photos/Khqmo4T-rs0",
                "download": "https://unsplash.com/photos/Khqmo4T-rs0/download",
                "download_location": "https://api.unsplash.com/photos/Khqmo4T-rs0/download"
            },
            "categories": [],
            "sponsored": false,
            "sponsored_by": null,
            "sponsored_impressions_id": null,
            "likes": 525,
            "liked_by_user": false,
            "current_user_collections": [],
            "user": {
                "id": "xH-ymDMRF4o",
                "updated_at": "2019-04-12T14:38:41-04:00",
                "username": "jcgellidon",
                "name": "JC Gellidon",
                "first_name": "JC",
                "last_name": "Gellidon",
                "twitter_username": "jcgellidon",
                "portfolio_url": "http://www.fb.com/imjcgellidon",
                "bio": "An independent photographer and a film maker based in Manila, Philippines. ",
                "location": "Makati, Philippines",
                "links": {
                    "self": "https://api.unsplash.com/users/jcgellidon",
                    "html": "https://unsplash.com/@jcgellidon",
                    "photos": "https://api.unsplash.com/users/jcgellidon/photos",
                    "likes": "https://api.unsplash.com/users/jcgellidon/likes",
                    "portfolio": "https://api.unsplash.com/users/jcgellidon/portfolio",
                    "following": "https://api.unsplash.com/users/jcgellidon/following",
                    "followers": "https://api.unsplash.com/users/jcgellidon/followers"
                },
                "profile_image": {
                    "small": "https://images.unsplash.com/profile-fb-1502817706-2b51aa841673.jpg?ixlib=rb-1.2.1&q=80&fm=jpg&crop=faces&cs=tinysrgb&fit=crop&h=32&w=32",
                    "medium": "https://images.unsplash.com/profile-fb-1502817706-2b51aa841673.jpg?ixlib=rb-1.2.1&q=80&fm=jpg&crop=faces&cs=tinysrgb&fit=crop&h=64&w=64",
                    "large": "https://images.unsplash.com/profile-fb-1502817706-2b51aa841673.jpg?ixlib=rb-1.2.1&q=80&fm=jpg&crop=faces&cs=tinysrgb&fit=crop&h=128&w=128"
                },
                "instagram_username": "jcgellidon",
                "total_collections": 0,
                "total_likes": 115,
                "total_photos": 135,
                "accepted_tos": true
            },
            "tags": [
                {
                    "title": "night"
                },
                {
                    "title": "orange"
                },
                {
                    "title": "light"
                },
                {
                    "title": "dark"
                },
                {
                    "title": "black"
                },
                {
                    "title": "architecture"
                },
                {
                    "title": "minimal"
                },
                {
                    "title": "line"
                },
                {
                    "title": "geometry"
                },
                {
                    "title": "street photographer"
                },
                {
                    "title": "urbex"
                },
                {
                    "title": "urban"
                },
                {
                    "title": "makati"
                },
                {
                    "title": "rockwell"
                },
                {
                    "title": "philippines"
                },
                {
                    "title": "a7sii"
                },
                {
                    "title": "2470"
                },
                {
                    "title": "sel2470gm"
                },
                {
                    "title": "alpha"
                },
                {
                    "title": "sony"
                }
            ]
        },
        {
            "id": "VW8MUbHyxCU",
            "created_at": "2016-08-03T06:21:34-04:00",
            "updated_at": "2019-03-27T17:44:45-04:00",
            "width": 5000,
            "height": 2813,
            "color": "#10121E",
            "description": "Goodies from Top of the Rock",
            "alt_description": "Empire State Building",
            "urls": {
                "raw": "https://images.unsplash.com/photo-1470219556762-1771e7f9427d?ixlib=rb-1.2.1&ixid=eyJhcHBfaWQiOjY2Njc0fQ",
                "full": "https://images.unsplash.com/photo-1470219556762-1771e7f9427d?ixlib=rb-1.2.1&q=85&fm=jpg&crop=entropy&cs=srgb&ixid=eyJhcHBfaWQiOjY2Njc0fQ",
                "regular": "https://images.unsplash.com/photo-1470219556762-1771e7f9427d?ixlib=rb-1.2.1&q=80&fm=jpg&crop=entropy&cs=tinysrgb&w=1080&fit=max&ixid=eyJhcHBfaWQiOjY2Njc0fQ",
                "small": "https://images.unsplash.com/photo-1470219556762-1771e7f9427d?ixlib=rb-1.2.1&q=80&fm=jpg&crop=entropy&cs=tinysrgb&w=400&fit=max&ixid=eyJhcHBfaWQiOjY2Njc0fQ",
                "thumb": "https://images.unsplash.com/photo-1470219556762-1771e7f9427d?ixlib=rb-1.2.1&q=80&fm=jpg&crop=entropy&cs=tinysrgb&w=200&fit=max&ixid=eyJhcHBfaWQiOjY2Njc0fQ"
            },
            "links": {
                "self": "https://api.unsplash.com/photos/VW8MUbHyxCU",
                "html": "https://unsplash.com/photos/VW8MUbHyxCU",
                "download": "https://unsplash.com/photos/VW8MUbHyxCU/download",
                "download_location": "https://api.unsplash.com/photos/VW8MUbHyxCU/download"
            },
            "categories": [],
            "sponsored": false,
            "sponsored_by": null,
            "sponsored_impressions_id": null,
            "likes": 803,
            "liked_by_user": false,
            "current_user_collections": [],
            "user": {
                "id": "80-ARydt_YE",
                "updated_at": "2019-04-08T05:42:58-04:00",
                "username": "jonathan_christian_photography",
                "name": "jonathan riley",
                "first_name": "jonathan",
                "last_name": "riley",
                "twitter_username": "JonathanCRiley",
                "portfolio_url": "http://www.jonathanchristianphotography.co.uk",
                "bio": "Ex pro Contemporary and Ballet dancer turned photographer. My travels as a dancer took me allover the world, i always had camera with me so the transition to photographer was a natural one.",
                "location": "Derbyshire, Uk",
                "links": {
                    "self": "https://api.unsplash.com/users/jonathan_christian_photography",
                    "html": "https://unsplash.com/@jonathan_christian_photography",
                    "photos": "https://api.unsplash.com/users/jonathan_christian_photography/photos",
                    "likes": "https://api.unsplash.com/users/jonathan_christian_photography/likes",
                    "portfolio": "https://api.unsplash.com/users/jonathan_christian_photography/portfolio",
                    "following": "https://api.unsplash.com/users/jonathan_christian_photography/following",
                    "followers": "https://api.unsplash.com/users/jonathan_christian_photography/followers"
                },
                "profile_image": {
                    "small": "https://images.unsplash.com/profile-1472384957739-ebd709d621e3?ixlib=rb-1.2.1&q=80&fm=jpg&crop=faces&cs=tinysrgb&fit=crop&h=32&w=32",
                    "medium": "https://images.unsplash.com/profile-1472384957739-ebd709d621e3?ixlib=rb-1.2.1&q=80&fm=jpg&crop=faces&cs=tinysrgb&fit=crop&h=64&w=64",
                    "large": "https://images.unsplash.com/profile-1472384957739-ebd709d621e3?ixlib=rb-1.2.1&q=80&fm=jpg&crop=faces&cs=tinysrgb&fit=crop&h=128&w=128"
                },
                "instagram_username": "jonathan_riley_photography",
                "total_collections": 0,
                "total_likes": 0,
                "total_photos": 2,
                "accepted_tos": false
            },
            "tags": [
                {
                    "title": "skyscraper"
                },
                {
                    "title": "building"
                },
                {
                    "title": "skyline"
                },
                {
                    "title": "new york"
                },
                {
                    "title": "manhattan"
                },
                {
                    "title": "empire state building"
                },
                {
                    "title": "crowded"
                },
                {
                    "title": "tall"
                },
                {
                    "title": "nyc"
                },
                {
                    "title": "sunset"
                },
                {
                    "title": "urban"
                },
                {
                    "title": "cityscape"
                },
                {
                    "title": "the big apple"
                },
                {
                    "title": "downtown"
                },
                {
                    "title": "1 world trade centre"
                },
                {
                    "title": "world trade centre"
                },
                {
                    "title": "population"
                },
                {
                    "title": "sightseeing"
                },
                {
                    "title": "view"
                },
                {
                    "title": "lightning rod"
                }
            ]
        },
        {
            "id": "99wmYtakIyg",
            "created_at": "2018-06-02T12:15:27-04:00",
            "updated_at": "2019-03-27T18:14:57-04:00",
            "width": 3601,
            "height": 5402,
            "color": "#FBF9F7",
            "description": null,
            "alt_description": "Empire State Building",
            "urls": {
                "raw": "https://images.unsplash.com/photo-1527956041665-d7a1b380c460?ixlib=rb-1.2.1&ixid=eyJhcHBfaWQiOjY2Njc0fQ",
                "full": "https://images.unsplash.com/photo-1527956041665-d7a1b380c460?ixlib=rb-1.2.1&q=85&fm=jpg&crop=entropy&cs=srgb&ixid=eyJhcHBfaWQiOjY2Njc0fQ",
                "regular": "https://images.unsplash.com/photo-1527956041665-d7a1b380c460?ixlib=rb-1.2.1&q=80&fm=jpg&crop=entropy&cs=tinysrgb&w=1080&fit=max&ixid=eyJhcHBfaWQiOjY2Njc0fQ",
                "small": "https://images.unsplash.com/photo-1527956041665-d7a1b380c460?ixlib=rb-1.2.1&q=80&fm=jpg&crop=entropy&cs=tinysrgb&w=400&fit=max&ixid=eyJhcHBfaWQiOjY2Njc0fQ",
                "thumb": "https://images.unsplash.com/photo-1527956041665-d7a1b380c460?ixlib=rb-1.2.1&q=80&fm=jpg&crop=entropy&cs=tinysrgb&w=200&fit=max&ixid=eyJhcHBfaWQiOjY2Njc0fQ"
            },
            "links": {
                "self": "https://api.unsplash.com/photos/99wmYtakIyg",
                "html": "https://unsplash.com/photos/99wmYtakIyg",
                "download": "https://unsplash.com/photos/99wmYtakIyg/download",
                "download_location": "https://api.unsplash.com/photos/99wmYtakIyg/download"
            },
            "categories": [],
            "sponsored": false,
            "sponsored_by": null,
            "sponsored_impressions_id": null,
            "likes": 358,
            "liked_by_user": false,
            "current_user_collections": [],
            "user": {
                "id": "F07WHhGvxRA",
                "updated_at": "2019-04-14T16:41:16-04:00",
                "username": "oskarssylwan",
                "name": "Oskars Sylwan",
                "first_name": "Oskars",
                "last_name": "Sylwan",
                "twitter_username": "oskarssylwan",
                "portfolio_url": "https://www.instagram.com/oskarssylwan/",
                "bio": "Creator and minimalist",
                "location": "Sweden",
                "links": {
                    "self": "https://api.unsplash.com/users/oskarssylwan",
                    "html": "https://unsplash.com/@oskarssylwan",
                    "photos": "https://api.unsplash.com/users/oskarssylwan/photos",
                    "likes": "https://api.unsplash.com/users/oskarssylwan/likes",
                    "portfolio": "https://api.unsplash.com/users/oskarssylwan/portfolio",
                    "following": "https://api.unsplash.com/users/oskarssylwan/following",
                    "followers": "https://api.unsplash.com/users/oskarssylwan/followers"
                },
                "profile_image": {
                    "small": "https://images.unsplash.com/profile-1518539700136-581e95deadd6?ixlib=rb-1.2.1&q=80&fm=jpg&crop=faces&cs=tinysrgb&fit=crop&h=32&w=32",
                    "medium": "https://images.unsplash.com/profile-1518539700136-581e95deadd6?ixlib=rb-1.2.1&q=80&fm=jpg&crop=faces&cs=tinysrgb&fit=crop&h=64&w=64",
                    "large": "https://images.unsplash.com/profile-1518539700136-581e95deadd6?ixlib=rb-1.2.1&q=80&fm=jpg&crop=faces&cs=tinysrgb&fit=crop&h=128&w=128"
                },
                "instagram_username": "oskarssylwan",
                "total_collections": 4,
                "total_likes": 35,
                "total_photos": 58,
                "accepted_tos": false
            },
            "tags": [
                {
                    "title": "street"
                },
                {
                    "title": "building"
                },
                {
                    "title": "tree"
                },
                {
                    "title": "urban"
                },
                {
                    "title": "architecture"
                },
                {
                    "title": "modern design"
                },
                {
                    "title": "sign"
                },
                {
                    "title": "car"
                },
                {
                    "title": "vehicle"
                },
                {
                    "title": "travel"
                },
                {
                    "title": "transport"
                },
                {
                    "title": "perspective"
                },
                {
                    "title": "outdoors"
                },
                {
                    "title": "photo"
                },
                {
                    "title": "take"
                },
                {
                    "title": "to"
                },
                {
                    "title": "place"
                },
                {
                    "title": "hipster"
                },
                {
                    "title": "busy"
                },
                {
                    "title": "highrise"
                }
            ]
        },
        {
            "id": "igK8lcBHaHE",
            "created_at": "2016-03-03T13:44:36-05:00",
            "updated_at": "2019-03-27T17:42:17-04:00",
            "width": 5176,
            "height": 3451,
            "color": "#0E1319",
            "description": "San Francisco skyline",
            "alt_description": "cityscape photography of high-rise building",
            "urls": {
                "raw": "https://images.unsplash.com/photo-1457030642598-b037296c9296?ixlib=rb-1.2.1&ixid=eyJhcHBfaWQiOjY2Njc0fQ",
                "full": "https://images.unsplash.com/photo-1457030642598-b037296c9296?ixlib=rb-1.2.1&q=85&fm=jpg&crop=entropy&cs=srgb&ixid=eyJhcHBfaWQiOjY2Njc0fQ",
                "regular": "https://images.unsplash.com/photo-1457030642598-b037296c9296?ixlib=rb-1.2.1&q=80&fm=jpg&crop=entropy&cs=tinysrgb&w=1080&fit=max&ixid=eyJhcHBfaWQiOjY2Njc0fQ",
                "small": "https://images.unsplash.com/photo-1457030642598-b037296c9296?ixlib=rb-1.2.1&q=80&fm=jpg&crop=entropy&cs=tinysrgb&w=400&fit=max&ixid=eyJhcHBfaWQiOjY2Njc0fQ",
                "thumb": "https://images.unsplash.com/photo-1457030642598-b037296c9296?ixlib=rb-1.2.1&q=80&fm=jpg&crop=entropy&cs=tinysrgb&w=200&fit=max&ixid=eyJhcHBfaWQiOjY2Njc0fQ"
            },
            "links": {
                "self": "https://api.unsplash.com/photos/igK8lcBHaHE",
                "html": "https://unsplash.com/photos/igK8lcBHaHE",
                "download": "https://unsplash.com/photos/igK8lcBHaHE/download",
                "download_location": "https://api.unsplash.com/photos/igK8lcBHaHE/download"
            },
            "categories": [],
            "sponsored": false,
            "sponsored_by": null,
            "sponsored_impressions_id": null,
            "likes": 169,
            "liked_by_user": false,
            "current_user_collections": [],
            "user": {
                "id": "Lu1VNlMAW6k",
                "updated_at": "2019-04-12T13:49:09-04:00",
                "username": "sgabriel",
                "name": "Sebastien Gabriel",
                "first_name": "Sebastien",
                "last_name": "Gabriel",
                "twitter_username": "KounterB",
                "portfolio_url": "https://twitter.com/kounterb",
                "bio": "Design at Google. Chrome OS, Chrome Browser, Android.",
                "location": "San Francisco",
                "links": {
                    "self": "https://api.unsplash.com/users/sgabriel",
                    "html": "https://unsplash.com/@sgabriel",
                    "photos": "https://api.unsplash.com/users/sgabriel/photos",
                    "likes": "https://api.unsplash.com/users/sgabriel/likes",
                    "portfolio": "https://api.unsplash.com/users/sgabriel/portfolio",
                    "following": "https://api.unsplash.com/users/sgabriel/following",
                    "followers": "https://api.unsplash.com/users/sgabriel/followers"
                },
                "profile_image": {
                    "small": "https://images.unsplash.com/profile-1498097438863-fdcea26b0a96?ixlib=rb-1.2.1&q=80&fm=jpg&crop=faces&cs=tinysrgb&fit=crop&h=32&w=32",
                    "medium": "https://images.unsplash.com/profile-1498097438863-fdcea26b0a96?ixlib=rb-1.2.1&q=80&fm=jpg&crop=faces&cs=tinysrgb&fit=crop&h=64&w=64",
                    "large": "https://images.unsplash.com/profile-1498097438863-fdcea26b0a96?ixlib=rb-1.2.1&q=80&fm=jpg&crop=faces&cs=tinysrgb&fit=crop&h=128&w=128"
                },
                "instagram_username": "kounterb",
                "total_collections": 4,
                "total_likes": 0,
                "total_photos": 67,
                "accepted_tos": false
            },
            "tags": [
                {
                    "title": "city view"
                },
                {
                    "title": "city scape"
                },
                {
                    "title": "drone view"
                },
                {
                    "title": "aerial view"
                },
                {
                    "title": "city skyline"
                },
                {
                    "title": "skyline"
                },
                {
                    "title": "skyscraper"
                },
                {
                    "title": "building"
                },
                {
                    "title": "cityscape"
                },
                {
                    "title": "architecture"
                },
                {
                    "title": "structure"
                },
                {
                    "title": "district"
                },
                {
                    "title": "metropolitan"
                },
                {
                    "title": "downtown"
                },
                {
                    "title": "concretejungle"
                },
                {
                    "title": "aerial"
                },
                {
                    "title": "view"
                },
                {
                    "title": "high rise"
                },
                {
                    "title": "birdseyeview"
                },
                {
                    "title": "bay"
                }
            ]
        },
        {
            "id": "6NmnrAJPq7M",
            "created_at": "2017-01-05T16:58:31-05:00",
            "updated_at": "2019-03-27T17:48:09-04:00",
            "width": 5472,
            "height": 3648,
            "color": "#0B140E",
            "description": "This was taken from helicopter I have booked in NYC, it was great experience, highly recommend to book flight with FlyNyon.",
            "alt_description": "aerial photography of Empire State building",
            "urls": {
                "raw": "https://images.unsplash.com/photo-1483653364400-eedcfb9f1f88?ixlib=rb-1.2.1&ixid=eyJhcHBfaWQiOjY2Njc0fQ",
                "full": "https://images.unsplash.com/photo-1483653364400-eedcfb9f1f88?ixlib=rb-1.2.1&q=85&fm=jpg&crop=entropy&cs=srgb&ixid=eyJhcHBfaWQiOjY2Njc0fQ",
                "regular": "https://images.unsplash.com/photo-1483653364400-eedcfb9f1f88?ixlib=rb-1.2.1&q=80&fm=jpg&crop=entropy&cs=tinysrgb&w=1080&fit=max&ixid=eyJhcHBfaWQiOjY2Njc0fQ",
                "small": "https://images.unsplash.com/photo-1483653364400-eedcfb9f1f88?ixlib=rb-1.2.1&q=80&fm=jpg&crop=entropy&cs=tinysrgb&w=400&fit=max&ixid=eyJhcHBfaWQiOjY2Njc0fQ",
                "thumb": "https://images.unsplash.com/photo-1483653364400-eedcfb9f1f88?ixlib=rb-1.2.1&q=80&fm=jpg&crop=entropy&cs=tinysrgb&w=200&fit=max&ixid=eyJhcHBfaWQiOjY2Njc0fQ"
            },
            "links": {
                "self": "https://api.unsplash.com/photos/6NmnrAJPq7M",
                "html": "https://unsplash.com/photos/6NmnrAJPq7M",
                "download": "https://unsplash.com/photos/6NmnrAJPq7M/download",
                "download_location": "https://api.unsplash.com/photos/6NmnrAJPq7M/download"
            },
            "categories": [],
            "sponsored": false,
            "sponsored_by": null,
            "sponsored_impressions_id": null,
            "likes": 414,
            "liked_by_user": false,
            "current_user_collections": [],
            "user": {
                "id": "WD8AXrvO9Qc",
                "updated_at": "2019-03-26T04:35:44-04:00",
                "username": "thomashabr",
                "name": "Thomas Habr",
                "first_name": "Thomas",
                "last_name": "Habr",
                "twitter_username": "ThomasHabr",
                "portfolio_url": "http://thomashabr.com",
                "bio": "Designer & Photographer based in Prague.\r\n\r\nEmail – hello@thomashabr.com (PayPal Donations welcomed) Instagram – @thomashabr",
                "location": "Prague, Czech Republic",
                "links": {
                    "self": "https://api.unsplash.com/users/thomashabr",
                    "html": "https://unsplash.com/@thomashabr",
                    "photos": "https://api.unsplash.com/users/thomashabr/photos",
                    "likes": "https://api.unsplash.com/users/thomashabr/likes",
                    "portfolio": "https://api.unsplash.com/users/thomashabr/portfolio",
                    "following": "https://api.unsplash.com/users/thomashabr/following",
                    "followers": "https://api.unsplash.com/users/thomashabr/followers"
                },
                "profile_image": {
                    "small": "https://images.unsplash.com/profile-fb-1483653065-09a2e3215c0a.jpg?ixlib=rb-1.2.1&q=80&fm=jpg&crop=faces&cs=tinysrgb&fit=crop&h=32&w=32",
                    "medium": "https://images.unsplash.com/profile-fb-1483653065-09a2e3215c0a.jpg?ixlib=rb-1.2.1&q=80&fm=jpg&crop=faces&cs=tinysrgb&fit=crop&h=64&w=64",
                    "large": "https://images.unsplash.com/profile-fb-1483653065-09a2e3215c0a.jpg?ixlib=rb-1.2.1&q=80&fm=jpg&crop=faces&cs=tinysrgb&fit=crop&h=128&w=128"
                },
                "instagram_username": "thomashabr",
                "total_collections": 0,
                "total_likes": 3,
                "total_photos": 10,
                "accepted_tos": true
            },
            "tags": [
                {
                    "title": "skyscraper"
                },
                {
                    "title": "water"
                },
                {
                    "title": "waterfront"
                },
                {
                    "title": "river"
                },
                {
                    "title": "skyline"
                },
                {
                    "title": "building"
                },
                {
                    "title": "sky"
                },
                {
                    "title": "cloud"
                },
                {
                    "title": "outdoor"
                },
                {
                    "title": "sunset"
                },
                {
                    "title": "landscape"
                },
                {
                    "title": "downtown"
                },
                {
                    "title": "clear sky"
                },
                {
                    "title": "street"
                },
                {
                    "title": "chrysler building"
                },
                {
                    "title": "empire state building"
                },
                {
                    "title": "helicopter"
                },
                {
                    "title": "city view"
                },
                {
                    "title": "united state"
                },
                {
                    "title": "ny"
                }
            ]
        }
    ]
}
